pysplashsurf-0.14.0.0.dist-info/METADATA
pysplashsurf-0.14.0.0.dist-info/WHEEL
pysplashsurf-0.14.0.0.dist-info/entry_points.txt
pysplashsurf/__init__.py
pysplashsurf/bgeo.py
pysplashsurf/docs/Makefile
pysplashsurf/docs/make.bat
pysplashsurf/docs/requirements.txt
pysplashsurf/docs/source/api.rst
pysplashsurf/docs/source/classes.rst
pysplashsurf/docs/source/conf.py
pysplashsurf/docs/source/functions.rst
pysplashsurf/docs/source/index.md
pysplashsurf/py.typed
pysplashsurf/pysplashsurf.abi3.so
pysplashsurf/pysplashsurf.pyi
pysplashsurf-0.14.0.0.dist-info/RECORD
