Metadata-Version: 2.4
Name: pysplashsurf
Version: 0.14.0.0
Classifier: Programming Language :: Rust
Classifier: Programming Language :: Python :: Implementation :: CPython
Classifier: Programming Language :: Python :: Implementation :: PyPy
Classifier: Programming Language :: Python :: 3
Classifier: Programming Language :: Python :: 3.10
Classifier: Programming Language :: Python :: 3.11
Classifier: Programming Language :: Python :: 3.12
Classifier: Topic :: Scientific/Engineering
Classifier: Topic :: Scientific/Engineering :: Physics
Classifier: Topic :: Scientific/Engineering :: Visualization
Classifier: Topic :: Utilities
Requires-Dist: numpy
Requires-Dist: meshio ; extra == 'meshio'
Provides-Extra: meshio
Summary: Python bindings for splashsurf, a surface reconstruction library for SPH simulations.
Keywords: surface reconstruction,marching cubes,sph,fluid,particles,mesh,splashsurf,splishsplash
Author: Interactive Computer Graphics, Fabian Löschner
License-Expression: MIT
Requires-Python: >=3.10
Project-URL: Homepage, https://splashsurf.physics-simulation.org/
Project-URL: Repository, https://github.com/InteractiveComputerGraphics/splashsurf.git
Project-URL: Documentation, https://pysplashsurf.readthedocs.io/
